setup.py
probability_simba/Binomialdistribution.py
probability_simba/Gaussiandistribution.py
probability_simba/Generaldistribution.py
probability_simba/__init__.py
probability_simba.egg-info/PKG-INFO
probability_simba.egg-info/SOURCES.txt
probability_simba.egg-info/dependency_links.txt
probability_simba.egg-info/not-zip-safe
probability_simba.egg-info/top_level.txt