Metadata-Version: 1.0
Name: probability-simba
Version: 0.2
Summary: Gaussian and Binomial distributions
Home-page: UNKNOWN
Author: Sudhanshu Kumar
Author-email: UNKNOWN
License: UNKNOWN
Platform: UNKNOWN
